hrds/__init__.py
hrds/hrds.py
hrds/raster.py
hrds/raster_buffer.py
HRDS-0.1.4.dist-info/AUTHORS
HRDS-0.1.4.dist-info/LICENSE
HRDS-0.1.4.dist-info/METADATA
HRDS-0.1.4.dist-info/WHEEL
HRDS-0.1.4.dist-info/top_level.txt
HRDS-0.1.4.dist-info/RECORD
