Metadata-Version: 2.1
Name: HRDS
Version: 0.1.4
Summary: Read in multiple raster data files in a hierarchical fashion
Home-page: https://github.com/EnvModellingGroup/hrds
Author: Jon Hill
Author-email: Jon Hill <jon.hill@york.ac.uk>
Project-URL: Homepage, https://github.com/EnvModellingGroup/hrds
Keywords: raster,gis,modelling
Classifier: Development Status :: 4 - Beta
Classifier: Intended Audience :: Science/Research
Classifier: License :: OSI Approved :: GNU Lesser General Public License v3 (LGPLv3)
Classifier: Programming Language :: Python :: 3.6
Classifier: Topic :: Scientific/Engineering
Requires-Python: >=3.7
License-File: LICENSE
License-File: AUTHORS
